{"_path":"/projects/klimakalender","_dir":"projects","_draft":false,"_partial":false,"_locale":"","title":"klimakalender","description":"","thumbnail":"/images/221201-klimakalender-014.jpg","order":1,"body":{"type":"root","children":[{"type":"element","tag":"word-wave","props":{"link":"false","text":"entwurf"},"children":[]},{"type":"element","tag":"word-wave","props":{"link":"false","text":"druckdateien"},"children":[]},{"type":"element","tag":"gallery","props":{},"children":[{"type":"element","tag":"p","props":{},"children":[{"type":"element","tag":"img","props":{"alt":"Indymedia Mockup","src":"/images/indy-header.png"},"children":[]},{"type":"element","tag":"img","props":{"alt":"Indymedia Mockup","src":"/images/indy-header.png"},"children":[]},{"type":"element","tag":"img","props":{"alt":"Indymedia Mockup","src":"/images/231104-anna_geburtstag-012.jpg"},"children":[]},{"type":"element","tag":"img","props":{"alt":"Indymedia Mockup","src":"/images/indy-header.png"},"children":[]}]}]}],"toc":{"title":"","searchDepth":2,"depth":2,"links":[]}},"_type":"markdown","_id":"content:projects:klimakalender.md","_source":"content","_file":"projects/klimakalender.md","_extension":"md"}